{
	"elements": [
		{
			"data": {
				"Type": "block"
			},
			"weight": 1.0,
			"key": "blocks/ap_shell"
		},
		{
			"data": {
				"Type": "block"
			},
			"weight": 1.0,
			"key": "blocks/ap_shot"
		},
		{
			"data": {
				"Type": "block"
			},
			"weight": 1.0,
			"key": "blocks/autocannon_ammo_container"
		},
		{
			"data": {
				"Type": "block"
			},
			"weight": 1.0,
			"key": "blocks/autocannon_barrel_cast_mould"
		},
		{
			"data": {
				"Type": "block"
			},
			"weight": 1.0,
			"key": "blocks/autocannon_breech_cast_mould"
		},
		{
			"data": {
				"Type": "block"
			},
			"weight": 1.0,
			"key": "blocks/autocannon_recoil_spring_cast_mould"
		},
		{
			"data": {
				"Type": "block"
			},
			"weight": 1.0,
			"key": "blocks/bag_of_grapeshot"
		},
		{
			"data": {
				"Type": "block"
			},
			"weight": 1.0,
			"key": "blocks/basin_foundry_lid"
		},
		{
			"data": {
				"Type": "block"
			},
			"weight": 1.0,
			"key": "blocks/big_cartridge"
		},
		{
			"data": {
				"Type": "block"
			},
			"weight": 1.0,
			"key": "blocks/bronze_autocannon_barrel"
		},
		{
			"data": {
				"Type": "block"
			},
			"weight": 1.0,
			"key": "blocks/bronze_autocannon_breech"
		},
		{
			"data": {
				"Type": "block"
			},
			"weight": 1.0,
			"key": "blocks/bronze_autocannon_recoil_spring"
		},
		{
			"data": {
				"Type": "block"
			},
			"weight": 1.0,
			"key": "blocks/bronze_block"
		},
		{
			"data": {
				"Type": "block"
			},
			"weight": 1.0,
			"key": "blocks/bronze_cannon_barrel"
		},
		{
			"data": {
				"Type": "block"
			},
			"weight": 1.0,
			"key": "blocks/bronze_cannon_chamber"
		},
		{
			"data": {
				"Type": "block"
			},
			"weight": 1.0,
			"key": "blocks/bronze_cannon_end"
		},
		{
			"data": {
				"Type": "block"
			},
			"weight": 1.0,
			"key": "blocks/bronze_quickfiring_breech"
		},
		{
			"data": {
				"Type": "block"
			},
			"weight": 1.0,
			"key": "blocks/bronze_sliding_breech"
		},
		{
			"data": {
				"Type": "block"
			},
			"weight": 1.0,
			"key": "blocks/built_up_cannon"
		},
		{
			"data": {
				"Type": "block"
			},
			"weight": 1.0,
			"key": "blocks/built_up_nethersteel_cannon_barrel"
		},
		{
			"data": {
				"Type": "block"
			},
			"weight": 1.0,
			"key": "blocks/built_up_nethersteel_cannon_chamber"
		},
		{
			"data": {
				"Type": "block"
			},
			"weight": 1.0,
			"key": "blocks/built_up_steel_cannon_barrel"
		},
		{
			"data": {
				"Type": "block"
			},
			"weight": 1.0,
			"key": "blocks/built_up_steel_cannon_chamber"
		},
		{
			"data": {
				"Type": "block"
			},
			"weight": 1.0,
			"key": "blocks/cannon_builder"
		},
		{
			"data": {
				"Type": "block"
			},
			"weight": 1.0,
			"key": "blocks/cannon_builder_head"
		},
		{
			"data": {
				"Type": "block"
			},
			"weight": 1.0,
			"key": "blocks/cannon_carriage"
		},
		{
			"data": {
				"Type": "block"
			},
			"weight": 1.0,
			"key": "blocks/cannon_cast"
		},
		{
			"data": {
				"Type": "block"
			},
			"weight": 1.0,
			"key": "blocks/cannon_drill"
		},
		{
			"data": {
				"Type": "block"
			},
			"weight": 1.0,
			"key": "blocks/cannon_drill_bit"
		},
		{
			"data": {
				"Type": "block"
			},
			"weight": 1.0,
			"key": "blocks/cannon_end_cast_mould"
		},
		{
			"data": {
				"Type": "block"
			},
			"weight": 1.0,
			"key": "blocks/cannon_loader"
		},
		{
			"data": {
				"Type": "block"
			},
			"weight": 1.0,
			"key": "blocks/cannon_mount"
		},
		{
			"data": {
				"Type": "block"
			},
			"weight": 1.0,
			"key": "blocks/cannon_mount_extension"
		},
		{
			"data": {
				"Type": "block"
			},
			"weight": 1.0,
			"key": "blocks/cast_iron_autocannon_barrel"
		},
		{
			"data": {
				"Type": "block"
			},
			"weight": 1.0,
			"key": "blocks/cast_iron_autocannon_breech"
		},
		{
			"data": {
				"Type": "block"
			},
			"weight": 1.0,
			"key": "blocks/cast_iron_autocannon_recoil_spring"
		},
		{
			"data": {
				"Type": "block"
			},
			"weight": 1.0,
			"key": "blocks/cast_iron_block"
		},
		{
			"data": {
				"Type": "block"
			},
			"weight": 1.0,
			"key": "blocks/cast_iron_cannon_barrel"
		},
		{
			"data": {
				"Type": "block"
			},
			"weight": 1.0,
			"key": "blocks/cast_iron_cannon_chamber"
		},
		{
			"data": {
				"Type": "block"
			},
			"weight": 1.0,
			"key": "blocks/cast_iron_cannon_end"
		},
		{
			"data": {
				"Type": "block"
			},
			"weight": 1.0,
			"key": "blocks/cast_iron_quickfiring_breech"
		},
		{
			"data": {
				"Type": "block"
			},
			"weight": 1.0,
			"key": "blocks/cast_iron_sliding_breech"
		},
		{
			"data": {
				"Type": "block"
			},
			"weight": 1.0,
			"key": "blocks/casting_sand"
		},
		{
			"data": {
				"Type": "block"
			},
			"weight": 1.0,
			"key": "blocks/creative_autocannon_ammo_container"
		},
		{
			"data": {
				"Type": "block"
			},
			"weight": 1.0,
			"key": "blocks/drop_mortar_shell"
		},
		{
			"data": {
				"Type": "block"
			},
			"weight": 1.0,
			"key": "blocks/finished_cannon_cast"
		},
		{
			"data": {
				"Type": "block"
			},
			"weight": 1.0,
			"key": "blocks/fixed_cannon_mount"
		},
		{
			"data": {
				"Type": "block"
			},
			"weight": 1.0,
			"key": "blocks/fluid_shell"
		},
		{
			"data": {
				"Type": "block"
			},
			"weight": 1.0,
			"key": "blocks/he_shell"
		},
		{
			"data": {
				"Type": "block"
			},
			"weight": 1.0,
			"key": "blocks/incomplete_bronze_autocannon_breech"
		},
		{
			"data": {
				"Type": "block"
			},
			"weight": 1.0,
			"key": "blocks/incomplete_bronze_autocannon_recoil_spring"
		},
		{
			"data": {
				"Type": "block"
			},
			"weight": 1.0,
			"key": "blocks/incomplete_bronze_sliding_breech"
		},
		{
			"data": {
				"Type": "block"
			},
			"weight": 1.0,
			"key": "blocks/incomplete_cast_iron_autocannon_breech"
		},
		{
			"data": {
				"Type": "block"
			},
			"weight": 1.0,
			"key": "blocks/incomplete_cast_iron_autocannon_recoil_spring"
		},
		{
			"data": {
				"Type": "block"
			},
			"weight": 1.0,
			"key": "blocks/incomplete_cast_iron_sliding_breech"
		},
		{
			"data": {
				"Type": "block"
			},
			"weight": 1.0,
			"key": "blocks/incomplete_nethersteel_screw_breech"
		},
		{
			"data": {
				"Type": "block"
			},
			"weight": 1.0,
			"key": "blocks/incomplete_steel_autocannon_breech"
		},
		{
			"data": {
				"Type": "block"
			},
			"weight": 1.0,
			"key": "blocks/incomplete_steel_autocannon_recoil_spring"
		},
		{
			"data": {
				"Type": "block"
			},
			"weight": 1.0,
			"key": "blocks/incomplete_steel_screw_breech"
		},
		{
			"data": {
				"Type": "block"
			},
			"weight": 1.0,
			"key": "blocks/incomplete_steel_sliding_breech"
		},
		{
			"data": {
				"Type": "block"
			},
			"weight": 1.0,
			"key": "blocks/large_cast_mould"
		},
		{
			"data": {
				"Type": "block"
			},
			"weight": 1.0,
			"key": "blocks/large_nethersteel_cannon_layer"
		},
		{
			"data": {
				"Type": "block"
			},
			"weight": 1.0,
			"key": "blocks/large_steel_cannon_layer"
		},
		{
			"data": {
				"Type": "block"
			},
			"weight": 1.0,
			"key": "blocks/log_cannon_chamber"
		},
		{
			"data": {
				"Type": "block"
			},
			"weight": 1.0,
			"key": "blocks/log_cannon_end"
		},
		{
			"data": {
				"Type": "block"
			},
			"weight": 1.0,
			"key": "blocks/medium_cast_mould"
		},
		{
			"data": {
				"Type": "block"
			},
			"weight": 1.0,
			"key": "blocks/medium_nethersteel_cannon_layer"
		},
		{
			"data": {
				"Type": "block"
			},
			"weight": 1.0,
			"key": "blocks/medium_steel_cannon_layer"
		},
		{
			"data": {
				"Type": "block"
			},
			"weight": 1.0,
			"key": "blocks/mortar_stone"
		},
		{
			"data": {
				"Type": "block"
			},
			"weight": 1.0,
			"key": "blocks/mortar_stone_projectile"
		},
		{
			"data": {
				"Type": "block"
			},
			"weight": 1.0,
			"key": "blocks/nethersteel_block"
		},
		{
			"data": {
				"Type": "block"
			},
			"weight": 1.0,
			"key": "blocks/nethersteel_cannon_barrel"
		},
		{
			"data": {
				"Type": "block"
			},
			"weight": 1.0,
			"key": "blocks/nethersteel_cannon_chamber"
		},
		{
			"data": {
				"Type": "block"
			},
			"weight": 1.0,
			"key": "blocks/nethersteel_screw_breech"
		},
		{
			"data": {
				"Type": "block"
			},
			"weight": 1.0,
			"key": "blocks/powder_charge"
		},
		{
			"data": {
				"Type": "block"
			},
			"weight": 1.0,
			"key": "blocks/ram_head"
		},
		{
			"data": {
				"Type": "block"
			},
			"weight": 1.0,
			"key": "blocks/screw_breech_cast_mould"
		},
		{
			"data": {
				"Type": "block"
			},
			"weight": 1.0,
			"key": "blocks/shrapnel_shell"
		},
		{
			"data": {
				"Type": "block"
			},
			"weight": 1.0,
			"key": "blocks/sliding_breech_cast_mould"
		},
		{
			"data": {
				"Type": "block"
			},
			"weight": 1.0,
			"key": "blocks/small_cast_mould"
		},
		{
			"data": {
				"Type": "block"
			},
			"weight": 1.0,
			"key": "blocks/small_nethersteel_cannon_layer"
		},
		{
			"data": {
				"Type": "block"
			},
			"weight": 1.0,
			"key": "blocks/small_steel_cannon_layer"
		},
		{
			"data": {
				"Type": "block"
			},
			"weight": 1.0,
			"key": "blocks/smoke_shell"
		},
		{
			"data": {
				"Type": "block"
			},
			"weight": 1.0,
			"key": "blocks/solid_shot"
		},
		{
			"data": {
				"Type": "block"
			},
			"weight": 1.0,
			"key": "blocks/steel_autocannon_barrel"
		},
		{
			"data": {
				"Type": "block"
			},
			"weight": 1.0,
			"key": "blocks/steel_autocannon_breech"
		},
		{
			"data": {
				"Type": "block"
			},
			"weight": 1.0,
			"key": "blocks/steel_autocannon_recoil_spring"
		},
		{
			"data": {
				"Type": "block"
			},
			"weight": 1.0,
			"key": "blocks/steel_block"
		},
		{
			"data": {
				"Type": "block"
			},
			"weight": 1.0,
			"key": "blocks/steel_cannon_barrel"
		},
		{
			"data": {
				"Type": "block"
			},
			"weight": 1.0,
			"key": "blocks/steel_cannon_chamber"
		},
		{
			"data": {
				"Type": "block"
			},
			"weight": 1.0,
			"key": "blocks/steel_quickfiring_breech"
		},
		{
			"data": {
				"Type": "block"
			},
			"weight": 1.0,
			"key": "blocks/steel_screw_breech"
		},
		{
			"data": {
				"Type": "block"
			},
			"weight": 1.0,
			"key": "blocks/steel_sliding_breech"
		},
		{
			"data": {
				"Type": "block"
			},
			"weight": 1.0,
			"key": "blocks/thick_nethersteel_cannon_chamber"
		},
		{
			"data": {
				"Type": "block"
			},
			"weight": 1.0,
			"key": "blocks/thick_steel_cannon_chamber"
		},
		{
			"data": {
				"Type": "block"
			},
			"weight": 1.0,
			"key": "blocks/traffic_cone"
		},
		{
			"data": {
				"Type": "block"
			},
			"weight": 1.0,
			"key": "blocks/unbored_bronze_autocannon_barrel"
		},
		{
			"data": {
				"Type": "block"
			},
			"weight": 1.0,
			"key": "blocks/unbored_bronze_autocannon_breech"
		},
		{
			"data": {
				"Type": "block"
			},
			"weight": 1.0,
			"key": "blocks/unbored_bronze_autocannon_recoil_spring"
		},
		{
			"data": {
				"Type": "block"
			},
			"weight": 1.0,
			"key": "blocks/unbored_bronze_cannon_barrel"
		},
		{
			"data": {
				"Type": "block"
			},
			"weight": 1.0,
			"key": "blocks/unbored_bronze_cannon_chamber"
		},
		{
			"data": {
				"Type": "block"
			},
			"weight": 1.0,
			"key": "blocks/unbored_bronze_sliding_breech"
		},
		{
			"data": {
				"Type": "block"
			},
			"weight": 1.0,
			"key": "blocks/unbored_cast_iron_autocannon_barrel"
		},
		{
			"data": {
				"Type": "block"
			},
			"weight": 1.0,
			"key": "blocks/unbored_cast_iron_autocannon_breech"
		},
		{
			"data": {
				"Type": "block"
			},
			"weight": 1.0,
			"key": "blocks/unbored_cast_iron_autocannon_recoil_spring"
		},
		{
			"data": {
				"Type": "block"
			},
			"weight": 1.0,
			"key": "blocks/unbored_cast_iron_cannon_barrel"
		},
		{
			"data": {
				"Type": "block"
			},
			"weight": 1.0,
			"key": "blocks/unbored_cast_iron_cannon_chamber"
		},
		{
			"data": {
				"Type": "block"
			},
			"weight": 1.0,
			"key": "blocks/unbored_cast_iron_sliding_breech"
		},
		{
			"data": {
				"Type": "block"
			},
			"weight": 1.0,
			"key": "blocks/unbored_large_nethersteel_cannon_layer"
		},
		{
			"data": {
				"Type": "block"
			},
			"weight": 1.0,
			"key": "blocks/unbored_large_steel_cannon_layer"
		},
		{
			"data": {
				"Type": "block"
			},
			"weight": 1.0,
			"key": "blocks/unbored_medium_nethersteel_cannon_layer"
		},
		{
			"data": {
				"Type": "block"
			},
			"weight": 1.0,
			"key": "blocks/unbored_medium_steel_cannon_layer"
		},
		{
			"data": {
				"Type": "block"
			},
			"weight": 1.0,
			"key": "blocks/unbored_nethersteel_screw_breech"
		},
		{
			"data": {
				"Type": "block"
			},
			"weight": 1.0,
			"key": "blocks/unbored_small_nethersteel_cannon_layer"
		},
		{
			"data": {
				"Type": "block"
			},
			"weight": 1.0,
			"key": "blocks/unbored_small_steel_cannon_layer"
		},
		{
			"data": {
				"Type": "block"
			},
			"weight": 1.0,
			"key": "blocks/unbored_steel_autocannon_barrel"
		},
		{
			"data": {
				"Type": "block"
			},
			"weight": 1.0,
			"key": "blocks/unbored_steel_autocannon_breech"
		},
		{
			"data": {
				"Type": "block"
			},
			"weight": 1.0,
			"key": "blocks/unbored_steel_autocannon_recoil_spring"
		},
		{
			"data": {
				"Type": "block"
			},
			"weight": 1.0,
			"key": "blocks/unbored_steel_screw_breech"
		},
		{
			"data": {
				"Type": "block"
			},
			"weight": 1.0,
			"key": "blocks/unbored_steel_sliding_breech"
		},
		{
			"data": {
				"Type": "block"
			},
			"weight": 1.0,
			"key": "blocks/unbored_very_large_nethersteel_cannon_layer"
		},
		{
			"data": {
				"Type": "block"
			},
			"weight": 1.0,
			"key": "blocks/unbored_very_large_steel_cannon_layer"
		},
		{
			"data": {
				"Type": "block"
			},
			"weight": 1.0,
			"key": "blocks/unbored_very_small_nethersteel_cannon_layer"
		},
		{
			"data": {
				"Type": "block"
			},
			"weight": 1.0,
			"key": "blocks/unbored_very_small_steel_cannon_layer"
		},
		{
			"data": {
				"Type": "block"
			},
			"weight": 1.0,
			"key": "blocks/very_large_cast_mould"
		},
		{
			"data": {
				"Type": "block"
			},
			"weight": 1.0,
			"key": "blocks/very_large_nethersteel_cannon_layer"
		},
		{
			"data": {
				"Type": "block"
			},
			"weight": 1.0,
			"key": "blocks/very_large_steel_cannon_layer"
		},
		{
			"data": {
				"Type": "block"
			},
			"weight": 1.0,
			"key": "blocks/very_small_cast_mould"
		},
		{
			"data": {
				"Type": "block"
			},
			"weight": 1.0,
			"key": "blocks/very_small_nethersteel_cannon_layer"
		},
		{
			"data": {
				"Type": "block"
			},
			"weight": 1.0,
			"key": "blocks/very_small_steel_cannon_layer"
		},
		{
			"data": {
				"Type": "block"
			},
			"weight": 1.0,
			"key": "blocks/worm_head"
		},
		{
			"data": {
				"Type": "block"
			},
			"weight": 1.0,
			"key": "blocks/wrought_iron_cannon_chamber"
		},
		{
			"data": {
				"Type": "block"
			},
			"weight": 1.0,
			"key": "blocks/wrought_iron_cannon_end"
		},
		{
			"data": {
				"Type": "block"
			},
			"weight": 1.0,
			"key": "blocks/wrought_iron_drop_mortar_end"
		},
		{
			"data": {
				"Type": "block"
			},
			"weight": 1.0,
			"key": "blocks/yaw_controller"
		},
		{
			"data": {
				"Type": "block"
			},
			"weight": 1.0,
			"key": "boring_scrap/unbored_bronze_autocannon_barrel"
		},
		{
			"data": {
				"Type": "block"
			},
			"weight": 1.0,
			"key": "boring_scrap/unbored_bronze_autocannon_breech"
		},
		{
			"data": {
				"Type": "block"
			},
			"weight": 1.0,
			"key": "boring_scrap/unbored_bronze_autocannon_recoil_spring"
		},
		{
			"data": {
				"Type": "block"
			},
			"weight": 1.0,
			"key": "boring_scrap/unbored_bronze_cannon_barrel"
		},
		{
			"data": {
				"Type": "block"
			},
			"weight": 1.0,
			"key": "boring_scrap/unbored_bronze_cannon_chamber"
		},
		{
			"data": {
				"Type": "block"
			},
			"weight": 1.0,
			"key": "boring_scrap/unbored_bronze_sliding_breech"
		},
		{
			"data": {
				"Type": "block"
			},
			"weight": 1.0,
			"key": "boring_scrap/unbored_cast_iron_autocannon_barrel"
		},
		{
			"data": {
				"Type": "block"
			},
			"weight": 1.0,
			"key": "boring_scrap/unbored_cast_iron_autocannon_breech"
		},
		{
			"data": {
				"Type": "block"
			},
			"weight": 1.0,
			"key": "boring_scrap/unbored_cast_iron_autocannon_recoil_spring"
		},
		{
			"data": {
				"Type": "block"
			},
			"weight": 1.0,
			"key": "boring_scrap/unbored_cast_iron_cannon_barrel"
		},
		{
			"data": {
				"Type": "block"
			},
			"weight": 1.0,
			"key": "boring_scrap/unbored_cast_iron_cannon_chamber"
		},
		{
			"data": {
				"Type": "block"
			},
			"weight": 1.0,
			"key": "boring_scrap/unbored_cast_iron_sliding_breech"
		},
		{
			"data": {
				"Type": "block"
			},
			"weight": 1.0,
			"key": "boring_scrap/unbored_large_nethersteel_cannon_layer"
		},
		{
			"data": {
				"Type": "block"
			},
			"weight": 1.0,
			"key": "boring_scrap/unbored_large_steel_cannon_layer"
		},
		{
			"data": {
				"Type": "block"
			},
			"weight": 1.0,
			"key": "boring_scrap/unbored_medium_nethersteel_cannon_layer"
		},
		{
			"data": {
				"Type": "block"
			},
			"weight": 1.0,
			"key": "boring_scrap/unbored_medium_steel_cannon_layer"
		},
		{
			"data": {
				"Type": "block"
			},
			"weight": 1.0,
			"key": "boring_scrap/unbored_nethersteel_screw_breech"
		},
		{
			"data": {
				"Type": "block"
			},
			"weight": 1.0,
			"key": "boring_scrap/unbored_small_nethersteel_cannon_layer"
		},
		{
			"data": {
				"Type": "block"
			},
			"weight": 1.0,
			"key": "boring_scrap/unbored_small_steel_cannon_layer"
		},
		{
			"data": {
				"Type": "block"
			},
			"weight": 1.0,
			"key": "boring_scrap/unbored_steel_autocannon_barrel"
		},
		{
			"data": {
				"Type": "block"
			},
			"weight": 1.0,
			"key": "boring_scrap/unbored_steel_autocannon_breech"
		},
		{
			"data": {
				"Type": "block"
			},
			"weight": 1.0,
			"key": "boring_scrap/unbored_steel_autocannon_recoil_spring"
		},
		{
			"data": {
				"Type": "block"
			},
			"weight": 1.0,
			"key": "boring_scrap/unbored_steel_screw_breech"
		},
		{
			"data": {
				"Type": "block"
			},
			"weight": 1.0,
			"key": "boring_scrap/unbored_steel_sliding_breech"
		},
		{
			"data": {
				"Type": "block"
			},
			"weight": 1.0,
			"key": "boring_scrap/unbored_very_large_nethersteel_cannon_layer"
		},
		{
			"data": {
				"Type": "block"
			},
			"weight": 1.0,
			"key": "boring_scrap/unbored_very_large_steel_cannon_layer"
		},
		{
			"data": {
				"Type": "block"
			},
			"weight": 1.0,
			"key": "boring_scrap/unbored_very_small_nethersteel_cannon_layer"
		},
		{
			"data": {
				"Type": "block"
			},
			"weight": 1.0,
			"key": "boring_scrap/unbored_very_small_steel_cannon_layer"
		}
	]
}
